pdf_essentials/__init__.py
pdf_essentials/core.py
pdf_essentials/custom_exceptions.py
pdf_essentials/utils.py
pdf_essentials-0.0.3.dist-info/METADATA
pdf_essentials-0.0.3.dist-info/WHEEL
pdf_essentials-0.0.3.dist-info/licenses/LICENSE
pdf_essentials-0.0.3.dist-info/RECORD
