Metadata-Version: 2.3
Name: pdf-essentials
Version: 0.0.3
Summary: An easy-to-use Python library for annotating, manipulating and processing PDF files
Project-URL: Homepage, https://github.com/Halvani/pdf-essentials
Project-URL: Bug Tracker, https://github.com/Halvani/pdf-essentials/issues
Author: Oren Halvani
License-File: LICENSE
Keywords: pdf-annotation,pdf-converter,pdf-crop-margins,pdf-highlighting,pdf-manipulation,pdf-manipulation-utitilies,pdf-merger,pdf-redaction
Classifier: Development Status :: 4 - Beta
Classifier: Intended Audience :: Developers
Classifier: License :: OSI Approved :: MIT License
Classifier: Operating System :: OS Independent
Classifier: Programming Language :: Python :: 3.9
Classifier: Programming Language :: Python :: 3.10
Classifier: Programming Language :: Python :: 3.11
Classifier: Programming Language :: Python :: 3.12
Requires-Python: >=3.9
Requires-Dist: ghostscript==0.7
Requires-Dist: matplotlib==3.8.3
Requires-Dist: pikepdf==9.1.1
Requires-Dist: pymupdf==1.24.9
Requires-Dist: pypdf2==3.0.1
Requires-Dist: reportlab==4.2.2
Requires-Dist: webcolors==1.13
